Demo_pkg/__init__.py
Demo_pkg/perceptron.py
Demo_pkg_sarikamohan08-0.0.2.dist-info/LICENSE
Demo_pkg_sarikamohan08-0.0.2.dist-info/METADATA
Demo_pkg_sarikamohan08-0.0.2.dist-info/WHEEL
Demo_pkg_sarikamohan08-0.0.2.dist-info/top_level.txt
Demo_pkg_sarikamohan08-0.0.2.dist-info/RECORD
