Metadata-Version: 2.1
Name: Demo-pkg-sarikamohan08
Version: 0.0.2
Summary: A small demo package
Home-page: https://github.com/sarikamohan08/Demo-pkg
Author: sarikamohan08
Author-email: sarikamohan08@gmail.com
License: UNKNOWN
Project-URL: Bug Tracker, https://github.com/sarikamohan08/Demo-pkg/issues
Platform: UNKNOWN
Classifier: Programming Language :: Python :: 3
Classifier: License :: OSI Approved :: MIT License
Classifier: Operating System :: OS Independent
Requires-Python: >=3.6
License-File: LICENSE
Requires-Dist: numpy (==1.21.5)
Requires-Dist: pandas (==1.1.5)
Requires-Dist: joblib (==1.1.0)
